deepi/f_yolo.py
ansghk-5.0.3.dist-info/METADATA
ansghk-5.0.3.dist-info/WHEEL
ansghk-5.0.3.dist-info/top_level.txt
ansghk-5.0.3.dist-info/RECORD
