Metadata-Version: 2.1
Name: ansghk
Version: 5.0.3
Summary: ansghk
Author: jinsoo
Author-email: deepi.contact.us@gmail.com
License: MIT
Requires-Python: >=3.8
